streamlit_pivottable/__init__.py
streamlit_pivottable/example.py
streamlit_pivottable/frontend/build/asset-manifest.json
streamlit_pivottable/frontend/build/bootstrap.min.css
streamlit_pivottable/frontend/build/index.html
streamlit_pivottable/frontend/build/static/css/main.fd21f2e2.css
streamlit_pivottable/frontend/build/static/css/main.fd21f2e2.css.map
streamlit_pivottable/frontend/build/static/js/main.0ff62cbb.js
streamlit_pivottable/frontend/build/static/js/main.0ff62cbb.js.LICENSE.txt
streamlit_pivottable/frontend/build/static/js/main.0ff62cbb.js.map
streamlit_pivottable/frontend/build/static/js/main.16ba20a0.js
streamlit_pivottable/frontend/build/static/js/main.16ba20a0.js.LICENSE.txt
streamlit_pivottable/frontend/build/static/js/main.16ba20a0.js.map
streamlit_pivottable/frontend/build/static/js/main.321dd089.js
streamlit_pivottable/frontend/build/static/js/main.321dd089.js.LICENSE.txt
streamlit_pivottable/frontend/build/static/js/main.321dd089.js.map
streamlit_pivottable/frontend/build/static/js/main.591ac790.js
streamlit_pivottable/frontend/build/static/js/main.591ac790.js.LICENSE.txt
streamlit_pivottable/frontend/build/static/js/main.591ac790.js.map
streamlit_pivottable/frontend/build/static/js/main.96983a67.js
streamlit_pivottable/frontend/build/static/js/main.96983a67.js.LICENSE.txt
streamlit_pivottable/frontend/build/static/js/main.96983a67.js.map
streamlit_pivottable/frontend/build/static/js/main.b2e7078e.js
streamlit_pivottable/frontend/build/static/js/main.b2e7078e.js.LICENSE.txt
streamlit_pivottable/frontend/build/static/js/main.b2e7078e.js.map
streamlit_pivottable/frontend/build/static/js/main.c7bd3349.js
streamlit_pivottable/frontend/build/static/js/main.c7bd3349.js.LICENSE.txt
streamlit_pivottable/frontend/build/static/js/main.c7bd3349.js.map
streamlit_pivottable/frontend/build/static/js/main.ee579d41.js
streamlit_pivottable/frontend/build/static/js/main.ee579d41.js.LICENSE.txt
streamlit_pivottable/frontend/build/static/js/main.ee579d41.js.map
streamlit_pivottable-0.2.1.dist-info/LICENSE
streamlit_pivottable-0.2.1.dist-info/METADATA
streamlit_pivottable-0.2.1.dist-info/WHEEL
streamlit_pivottable-0.2.1.dist-info/top_level.txt
streamlit_pivottable-0.2.1.dist-info/RECORD
